commitguard/__init__.py
commitguard/api/__init__.py
commitguard/api/git.py
commitguard/api/path.py
commitguard/cli/__init__.py
commitguard/cli/activate.py
commitguard/cli/check.py
commitguard/cli/plugins.py
commitguard/config.py
commitguard/errors.py
commitguard/extension/__init__.py
commitguard/extension/rich.py
commitguard/extension/terminal.py
commitguard/helper.py
commitguard/hooks.py
commitguard/precommit/__init__.py
commitguard/precommit/run.py
commitguard/precommit/template
commitguard/py.typed
commitguard/settings.py
commitguard/template.py
commitguard/terminal.py
commitguard/utils.py
commitguard-2.2.0.dist-info/LICENSE
commitguard-2.2.0.dist-info/METADATA
commitguard-2.2.0.dist-info/WHEEL
commitguard-2.2.0.dist-info/entry_points.txt
commitguard-2.2.0.dist-info/RECORD
